{"transcript":"antɾeˈnœɾ","exists":true,"definitions":["Spor dallarında sporcuları veya takımları çalıştıran, eğiten ve yöneten kimse.","Bir spor dalında uzmanlaşmış ve bu alanda başkalarını eğiten kişi."],"examples":["Antrenör, maçtan sonra oyuncularıyla konuştu.","Yeni antrenör, takıma farklı bir hava kattı.","Antrenör, genç yetenekleri keşfetmek için çok çalışıyor."],"lemma":"antrenör","lemmaPos":"noun","synonyms":["çalıştırıcı","eğitmen","hoca"],"number":"singular","pluralForm":"antrenörler","source":"antrenör"}