{"transcript":"cimyasal biɫeʃic","exists":true,"definitions":["İki veya daha fazla farklı elementin atomlarının belirli oranlarda kimyasal bağlarla birleşerek oluşturduğu saf madde.","Farklı elementlerin atomlarının belirli oranlarda bir araya gelmesiyle oluşan ve kendine özgü özellikleri olan madde."],"examples":["Su, bilinen en yaygın kimyasal bileşiklerden biridir.","Yeni bir kimyasal bileşik sentezlendi.","Bu kimyasal bileşik zehirli olabilir."],"lemma":"kimyasal bileşik","lemmaPos":"noun","synonyms":["bileşik","kimyevi bileşik"],"number":"singular","pluralForm":"kimyasal bileşikler","source":"kimyasal bileşik"}